README.md
setup.cfg
setup.py
WAF_Gauss/Binomialdistribution.py
WAF_Gauss/Gaussiandistribution.py
WAF_Gauss/Generaldistribution.py
WAF_Gauss/__init__.py
WAF_Gauss.egg-info/PKG-INFO
WAF_Gauss.egg-info/SOURCES.txt
WAF_Gauss.egg-info/dependency_links.txt
WAF_Gauss.egg-info/not-zip-safe
WAF_Gauss.egg-info/top_level.txt